{
    "description": {
        "image": "V006_77_0_00_04_03_13_0_c37_20201208_0004_S01_2.jpg",
        "date": "2020/12/08",
        "worker": "",
        "height": 4608,
        "width": 3456,
        "task": 77,
        "type": 0,
        "region": null
    },
    "annotations": {
        "disease": 0,
        "crop": 4,
        "area": 3,
        "grow": 13,
        "risk": 0,
        "points": [
            {
                "xtl": 160,
                "ytl": 736,
                "xbr": 3351,
                "ybr": 4108
            }
        ]
    }
}