{
    "description": {
        "image": "V006_77_1_07_04_02_13_1_3248b_20201219_121331.jpg",
        "date": "2020/12/19",
        "worker": "",
        "height": 3024,
        "width": 4032,
        "task": 77,
        "type": 1,
        "region": 5
    },
    "annotations": {
        "disease": 7,
        "crop": 4,
        "area": 2,
        "grow": 13,
        "risk": 1,
        "points": [
            {
                "xtl": 1840,
                "ytl": 1064,
                "xbr": 2400,
                "ybr": 1660
            }
        ]
    }
}