{
    "description": {
        "image": "V006_77_1_08_04_03_13_1_3108w_20201209_130.jpg",
        "date": "2020/12/09",
        "worker": "",
        "height": 1548,
        "width": 2064,
        "task": 77,
        "type": 1,
        "region": 5
    },
    "annotations": {
        "disease": 8,
        "crop": 4,
        "area": 3,
        "grow": 13,
        "risk": 1,
        "points": [
            {
                "xtl": 414,
                "ytl": 430,
                "xbr": 1968,
                "ybr": 1396
            }
        ]
    }
}