{
    "description": {
        "image": "V006_77_1_08_04_03_12_2_3742w_20201210_143.jpg",
        "date": "2020/12/10",
        "worker": "",
        "height": 1548,
        "width": 2064,
        "task": 77,
        "type": 1,
        "region": 5
    },
    "annotations": {
        "disease": 8,
        "crop": 4,
        "area": 3,
        "grow": 12,
        "risk": 2,
        "points": [
            {
                "xtl": 421,
                "ytl": 705,
                "xbr": 815,
                "ybr": 1548
            }
        ]
    }
}